{
  "version": "1.0.0",
  "restore": {
    "projectUniqueName": "C:\\Users\\Maksymilian Zawartko\\Documents\\Dokumenty\\studia\\lato 17-18\\POO\\8\\L8\\E2\\E2.csproj",
    "projectName": "E2",
    "projectPath": "C:\\Users\\Maksymilian Zawartko\\Documents\\Dokumenty\\studia\\lato 17-18\\POO\\8\\L8\\E2\\E2.csproj",
    "outputPath": "C:\\Users\\Maksymilian Zawartko\\Documents\\Dokumenty\\studia\\lato 17-18\\POO\\8\\L8\\E2\\obj\\",
    "projectStyle": "PackageReference",
    "fallbackFolders": [
      "C:\\Program Files\\dotnet\\sdk\\NuGetFallbackFolder"
    ],
    "originalTargetFrameworks": [
      "netcoreapp2.0"
    ],
    "frameworks": {
      "netcoreapp2.0": {
        "projectReferences": {}
      }
    },
    "warningProperties": {
      "warnAsError": [
        "NU1605"
      ]
    }
  },
  "frameworks": {
    "netcoreapp2.0": {
      "dependencies": {
        "Microsoft.NETCore.App": {
          "suppressParent": "All",
          "target": "Package",
          "version": "[2.0.0, )",
          "autoReferenced": true
        },
        "System.Data.SQLite.Core": {
          "target": "Package",
          "version": "[1.0.108, )"
        }
      },
      "imports": [
        "net461"
      ],
      "assetTargetFallback": true,
      "warn": true
    }
  }
}